Workbook

Sheet Instruções
A1: Saúde Pet | Levantamento de produtos do fornecedor
A2: Fornecedor 01: Casa de Rações Filhos de 4 Patas (Ribeirão Preto/SP) | Contato: (16) 99428-8613
A4: Margem padrão aplicada | B4: 0.4 | C4: Altere aqui para mudar a margem de toda a aba Catálogo de uma vez.
A6: Como usar esta planilha
A7: Células em AZUL | C7: são as que você preenche (custo, código de barras, estoque).
A8: Célula AMARELA (B4) | C8: é a margem padrão. Hoje está em 40%.
A9: Coluna J (Preço de venda) | C9: é calculada sozinha: custo x (1 + margem). Não digite nada nela.
A10: Coluna I (Margem) | C10: vem da margem padrão. Só edite se um item específico precisar de margem diferente.
A11: Coluna K (Preço na loja) | C11: é o preço de etiqueta que apareceu nas fotos. Serve de referência, não é o seu custo.
A12: Linha 3 do Catálogo | C12: é um EXEMPLO preenchido. Apague antes de subir para a plataforma.
A14: Roteiro do levantamento na loja
A15: 1. Peça a tabela de preços em arquivo (planilha, PDF ou foto legível). Confirme se o preço é de custo/atacado para você ou preço de balcão.
A16: 2. Confirme a condição comercial: prazo de pagamento, pedido mínimo, se o preço muda por volume e com que frequência a tabela é reajustada.
A17: 3. Passe corredor por corredor e fotografe: frente da embalagem, tabela nutricional e o código de barras. O EAN é o que evita cadastro duplicado depois.
A18: 4. Para cada item registre: marca, linha, sabor, público (cão/gato/filhote/adulto/castrado), peso e a unidade de venda (saco, pacote, unidade, fardo com X).
A19: 5. Anote a disponibilidade real. Produto que ele só traz sob encomenda precisa de aviso de prazo na plataforma.
A20: 6. Comece com os campeões de giro (rações 15 kg, tapete higiênico, areia, petiscos) e deixe acessórios e roupas para uma segunda leva.
A21: 7. Marque quem é frágil ou pesado. Saco de 15 kg muda a conta do frete e da sua logística de retirada.
A22: 8. Ao fechar, valide 5 itens do seu preço final contra o preço do mercado local. Margem de 40% em ração de marca costuma ficar acima do praticado.
A24: Origem dos dados
A25: Os produtos da aba Catálogo foram identificados a partir de 50 fotos tiradas na loja em 26/08/2026 (lote 1: Fotos 1 a 9; lote 2: IMG_4289 a IMG_4298; lote 3: IMG_4279 a IMG_4288; lote 4: IMG_4259 a IMG_4278; lote 5: 1 foto avulsa). Onde a embalagem apareceu parcialmente, o item está marcado como CONFIRMAR na coluna Observações.
A26: Os valores da coluna K são etiquetas visíveis nas fotos. Nenhum custo de fornecedor foi informado até aqui, por isso a coluna H está vazia.
A27: Pesos, sabores e códigos de barras precisam ser conferidos na embalagem física antes do cadastro definitivo.

Sheet Catálogo
A1: ID | B1: Categoria | C1: Marca | D1: Produto | E1: Variação / Sabor | F1: Peso / Tamanho | G1: Unidade de venda | H1: Custo fornecedor (R$) | I1: Margem | J1: Preço de venda (R$) | K1: Preço na loja (R$) | L1: Código de barras (EAN) | M1: Estoque | N1: Foto | O1: Observações
A2: EX | B2: Ração cão | C2: Golden (PremieRpet) | D2: Golden Formula Cães Adultos | E2: Frango e arroz - porte pequeno | F2: 15 kg | G2: Saco | H2: 150 | I2: =Instruções!$B$4 -> 0.4 | J2: =IF(H2="","",H2*(1+I2)) -> 210 | K2: 196.5 | L2: 7896588300000 | M2: 8 | N2: Foto 9 | O2: LINHA DE EXEMPLO - apague antes do cadastro
A3: 1 | B3: Ração cão | C3: Golden (PremieRpet) | D3: Golden Formula Cães Adultos | E3: Frango e arroz - porte pequeno | F3: 15 kg | G3: Saco | I3: =Instruções!$B$4 -> 0.4 | J3: =IF(H3="","",H3*(1+I3)) | K3: 196.5 | N3: Foto 9
A4: 2 | B4: Ração cão | C4: Golden (PremieRpet) | D4: Golden Formula Cães Adultos | E4: Frango e arroz | F4: 10,1 kg | G4: Saco | I4: =Instruções!$B$4 -> 0.4 | J4: =IF(H4="","",H4*(1+I4)) | N4: Foto 9 | O4: CONFIRMAR linha e público na embalagem
A5: 3 | B5: Ração cão | C5: Purina | D5: Dog Chow Adultos Minis e Pequenos | E5: Carne e frango | F5: 15 kg | G5: Saco | I5: =Instruções!$B$4 -> 0.4 | J5: =IF(H5="","",H5*(1+I5)) | K5: 175.9 | N5: Foto 9
A6: 4 | B6: Ração cão | C6: Vitta | D6: Vitta Natural Cães Adultos | E6: Frango e arroz - porte pequeno | F6: 15 kg | G6: Saco | I6: =Instruções!$B$4 -> 0.4 | J6: =IF(H6="","",H6*(1+I6)) | K6: 140 | N6: Foto 9
A7: 5 | B7: Ração cão | C7: Vitta | D7: Vitta Natural Cães Filhotes | E7: Frango e arroz - porte pequeno | F7: CONFIRMAR | G7: Saco | I7: =Instruções!$B$4 -> 0.4 | J7: =IF(H7="","",H7*(1+I7)) | N7: Foto 5 | O7: CONFIRMAR peso
A8: 6 | B8: Ração cão | C8: Flock | D8: Flock Adultos | E8: Carne | F8: 15 kg | G8: Saco | I8: =Instruções!$B$4 -> 0.4 | J8: =IF(H8="","",H8*(1+I8)) | K8: 77 | N8: Foto 9 | O8: Item de entrada, bom para atrair preço
A9: 7 | B9: Ração cão | C9: Nutriva | D9: Nutriva Select Adultos Pequeno Porte | E9: Frango e arroz | F9: 15 kg | G9: Saco | I9: =Instruções!$B$4 -> 0.4 | J9: =IF(H9="","",H9*(1+I9)) | N9: Foto 8 | O9: Premium especial, 24% proteína
A10: 8 | B10: Ração cão | C10: Spert | D10: Spert Cães Adultos | E10: Todos os portes | F10: 15 kg | G10: Saco | I10: =Instruções!$B$4 -> 0.4 | J10: =IF(H10="","",H10*(1+I10)) | N10: Foto 9 | O10: CONFIRMAR sabor
A11: 9 | B11: Ração cão | C11: Special Dog | D11: Special Dog Gold Adultos | E11: CONFIRMAR | F11: 15 kg | G11: Saco | I11: =Instruções!$B$4 -> 0.4 | J11: =IF(H11="","",H11*(1+I11)) | N11: Foto 9 | O11: CONFIRMAR sabor e linha
A12: 10 | B12: Ração cão | C12: Special Dog | D12: Special Dog Ultralife Premium Especial | E12: Frango - adultos raças pequenas | F12: 3 kg | G12: Saco | I12: =Instruções!$B$4 -> 0.4 | J12: =IF(H12="","",H12*(1+I12)) | N12: Foto 5 | O12: Zero corantes e aromatizantes
A13: 11 | B13: Ração cão | C13: Finotrato | D13: Finotrato Life Cães Adultos | E13: Cordeiro e arroz - raças pequenas e médias | F13: CONFIRMAR | G13: Saco | I13: =Instruções!$B$4 -> 0.4 | J13: =IF(H13="","",H13*(1+I13)) | N13: Foto 5 | O13: CONFIRMAR peso
A14: 12 | B14: Ração cão | C14: Finotrato | D14: Finotrato Life Cães Adultos | E14: Frango e arroz | F14: 15 kg | G14: Saco | I14: =Instruções!$B$4 -> 0.4 | J14: =IF(H14="","",H14*(1+I14)) | N14: Foto 9
A15: 13 | B15: Ração cão | C15: Begacão | D15: Begacão Premium Natural Adultos | E15: Todos os portes | F15: 7 kg | G15: Saco | I15: =Instruções!$B$4 -> 0.4 | J15: =IF(H15="","",H15*(1+I15)) | N15: Foto 5
A16: 14 | B16: Ração cão | C16: Dog Choni | D16: Dog Choni Cães Adultos | E16: Carne e arroz | F16: CONFIRMAR | G16: Saco | I16: =Instruções!$B$4 -> 0.4 | J16: =IF(H16="","",H16*(1+I16)) | N16: Fotos 5 e 9 | O16: CONFIRMAR grafia da marca e peso
A17: 15 | B17: Ração cão | C17: Grupo Tosi | D17: Naturale / Agromix Filhotes | E17: Todas as raças | F17: 10,1 kg | G17: Saco | I17: =Instruções!$B$4 -> 0.4 | J17: =IF(H17="","",H17*(1+I17)) | N17: Foto 5 | O17: CONFIRMAR nome exato da linha
A18: 16 | B18: Ração cão | C18: Grupo Tosi | D18: Linha com sulfato de condroitina | E18: Suporte articular | F18: 10,1 kg | G18: Saco | I18: =Instruções!$B$4 -> 0.4 | J18: =IF(H18="","",H18*(1+I18)) | N18: Foto 9 | O18: CONFIRMAR marca e nome completo
A19: 17 | B19: Ração gato | C19: Special Cat | D19: Special Cat Premium Gatos Filhotes | E19: Mix de carnes | F19: 10,1 kg | G19: Saco | I19: =Instruções!$B$4 -> 0.4 | J19: =IF(H19="","",H19*(1+I19)) | N19: Foto 5
A20: 18 | B20: Ração gato | C20: Special Cat | D20: Special Cat Premium Gatos Adultos | E20: Peixe | F20: 10,1 kg | G20: Saco | I20: =Instruções!$B$4 -> 0.4 | J20: =IF(H20="","",H20*(1+I20)) | N20: Foto 5 | O20: Aparece em duas variações de peixe, conferir
A21: 19 | B21: Ração gato | C21: Gran Plus | D21: Gran Plus Gourmet Gatos Adultos Castrados | E21: Salmão e frango | F21: CONFIRMAR | G21: Saco | I21: =Instruções!$B$4 -> 0.4 | J21: =IF(H21="","",H21*(1+I21)) | N21: Foto 5 | O21: CONFIRMAR peso
A22: 20 | B22: Ração gato | C22: Gran Plus | D22: Gran Plus Menu Gatos | E22: CONFIRMAR | F22: 10,1 kg | G22: Saco | I22: =Instruções!$B$4 -> 0.4 | J22: =IF(H22="","",H22*(1+I22)) | N22: Foto 9 | O22: CONFIRMAR sabor
A23: 21 | B23: Petisco cão | C23: Golden (PremieRpet) | D23: Golden Cookie | E23: Original - adultos porte pequeno | F23: CONFIRMAR | G23: Pacote | I23: =Instruções!$B$4 -> 0.4 | J23: =IF(H23="","",H23*(1+I23)) | K23: 19.5 | N23: Foto 6 | O23: CONFIRMAR gramatura
A24: 22 | B24: Petisco cão | C24: Special Dog | D24: Special Dog Ultralife Biscoitos Assados | E24: Frutas vermelhas | F24: CONFIRMAR | G24: Pacote | I24: =Instruções!$B$4 -> 0.4 | J24: =IF(H24="","",H24*(1+I24)) | K24: 16.3 | N24: Foto 6 | O24: Lançamento, CONFIRMAR gramatura
A25: 23 | B25: Petisco cão | C25: Doogs | D25: Doogs Biscoito | E25: Frango | F25: CONFIRMAR | G25: Pacote | I25: =Instruções!$B$4 -> 0.4 | J25: =IF(H25="","",H25*(1+I25)) | N25: Foto 5 | O25: CONFIRMAR gramatura
A26: 24 | B26: Petisco cão | C26: Doogs | D26: Doogs Original | E26: Alimento específico para cães | F26: CONFIRMAR | G26: Pacote | I26: =Instruções!$B$4 -> 0.4 | J26: =IF(H26="","",H26*(1+I26)) | N26: Foto 6 | O26: CONFIRMAR variação e preço
A27: 25 | B27: Higiene | C27: Brincalhão | D27: Tapete Higiênico Premium | E27: Cães | F27: Pacote com 6 un. | G27: Pacote | I27: =Instruções!$B$4 -> 0.4 | J27: =IF(H27="","",H27*(1+I27)) | K27: 19.8 | N27: Fotos 6 e 7 | O27: Alto giro, priorizar no cadastro
A28: 26 | B28: Higiene | C28: Brincat | D28: Areia Sanitária Biodegradável | E28: Capim-limão - grãos finos | F28: 2 kg | G28: Pacote | I28: =Instruções!$B$4 -> 0.4 | J28: =IF(H28="","",H28*(1+I28)) | N28: Foto 5
A29: 27 | B29: Higiene | C29: Brincat | D29: Areia Sanitária Biodegradável | E29: Natural - grãos finos | F29: 2 kg | G29: Pacote | I29: =Instruções!$B$4 -> 0.4 | J29: =IF(H29="","",H29*(1+I29)) | N29: Foto 5
A30: 28 | B30: Higiene | C30: Pipicat (Kelco) | D30: Aditivo Antiodor para Areia | E30: Campestre | F30: 500 g | G30: Pacote | I30: =Instruções!$B$4 -> 0.4 | J30: =IF(H30="","",H30*(1+I30)) | K30: 18 | N30: Foto 7
A31: 29 | B31: Higiene | C31: Pipicat (Kelco) | D31: Aditivo Antiodor para Areia | E31: Floral | F31: 500 g | G31: Pacote | I31: =Instruções!$B$4 -> 0.4 | J31: =IF(H31="","",H31*(1+I31)) | K31: 18 | N31: Foto 7
A32: 30 | B32: Outros animais | C32: CC-Albium | D32: Alimento Completo para Pássaros | E32: Papinha para filhotes | F32: 250 g | G32: Pote | I32: =Instruções!$B$4 -> 0.4 | J32: =IF(H32="","",H32*(1+I32)) | K32: 28.5 | N32: Fotos 6 e 7
A33: 31 | B33: Outros animais | C33: Indubras | D33: Suplemento vitamínico e mineral | E33: Animais de pequeno a grande porte | F33: CONFIRMAR | G33: Caixa | I33: =Instruções!$B$4 -> 0.4 | J33: =IF(H33="","",H33*(1+I33)) | N33: Foto 7 | O33: CONFIRMAR nome do produto (Ceva...)
A34: 32 | B34: Acessório | C34: Diversos | D34: Coleira de nylon estampada | E34: Diversas estampas e cores | F34: P / M / G | G34: Unidade | I34: =Instruções!$B$4 -> 0.4 | J34: =IF(H34="","",H34*(1+I34)) | N34: Fotos 1 e 2 | O34: Cadastrar por tamanho, foto por estampa
A35: 33 | B35: Acessório | C35: Diversos | D35: Guia de nylon estampada | E35: Diversas estampas e cores | F35: Único | G35: Unidade | I35: =Instruções!$B$4 -> 0.4 | J35: =IF(H35="","",H35*(1+I35)) | N35: Fotos 1 e 2
A36: 34 | B36: Acessório | C36: Diversos | D36: Peitoral com guia (conjunto) | E36: Nylon estampado | F36: P / M / G | G36: Conjunto | I36: =Instruções!$B$4 -> 0.4 | J36: =IF(H36="","",H36*(1+I36)) | N36: Fotos 1 e 2 | O36: Melhor vendido como kit na plataforma
A37: 35 | B37: Acessório | C37: Diversos | D37: Guia de corda com mosquetão | E37: Vermelha, azul, preta, rosa | F37: Único | G37: Unidade | I37: =Instruções!$B$4 -> 0.4 | J37: =IF(H37="","",H37*(1+I37)) | K37: 35 | N37: Foto 1 | O37: Etiqueta de 35,00 visível, CONFIRMAR a qual modelo pertence
A38: 36 | B38: Acessório | C38: Diversos | D38: Guia de corda com amortecedor (mola) | E38: Rosa e vermelha | F38: Único | G38: Unidade | I38: =Instruções!$B$4 -> 0.4 | J38: =IF(H38="","",H38*(1+I38)) | N38: Foto 1
A39: 37 | B39: Acessório | C39: Diversos | D39: Coleira de couro | E39: Vermelha | F39: M / G | G39: Unidade | I39: =Instruções!$B$4 -> 0.4 | J39: =IF(H39="","",H39*(1+I39)) | N39: Foto 1
A40: 38 | B40: Acessório | C40: Diversos | D40: Coleira/enforcador de corrente | E40: Metal | F40: M / G | G40: Unidade | I40: =Instruções!$B$4 -> 0.4 | J40: =IF(H40="","",H40*(1+I40)) | N40: Fotos 1 e 2
A41: 39 | B41: Acessório | C41: Diversos | D41: Cinto de segurança para pet | E41: Azul | F41: Único | G41: Unidade | I41: =Instruções!$B$4 -> 0.4 | J41: =IF(H41="","",H41*(1+I41)) | N41: Foto 4
A42: 40 | B42: Brinquedo | C42: Diversos | D42: Bola de corda com nó | E42: Laranja / verde | F42: Único | G42: Unidade | I42: =Instruções!$B$4 -> 0.4 | J42: =IF(H42="","",H42*(1+I42)) | N42: Foto 4
A43: 41 | B43: Vestuário | C43: Diversos | D43: Roupa pet soft/fleece | E43: Estampa nuvens rosa | F43: CONFIRMAR | G43: Unidade | I43: =Instruções!$B$4 -> 0.4 | J43: =IF(H43="","",H43*(1+I43)) | K43: 48 | N43: Foto 4 | O43: CONFIRMAR grade de tamanhos disponíveis
A44: 42 | B44: Vestuário | C44: Diversos | D44: Vestido pet estampado | E44: Floral laranja/azul | F44: CONFIRMAR | G44: Unidade | I44: =Instruções!$B$4 -> 0.4 | J44: =IF(H44="","",H44*(1+I44)) | N44: Foto 4 | O44: CONFIRMAR preço e tamanhos
A45: 43 | B45: Casa e conforto | C45: Diversos | D45: Casinha de madeira aglomerada | E45: Modelo iglu | F45: CONFIRMAR (nº) | G45: Unidade | I45: =Instruções!$B$4 -> 0.4 | J45: =IF(H45="","",H45*(1+I45)) | N45: Foto 3 | O45: Volumoso, avaliar retirada e frete
A46: 44 | B46: Casa e conforto | C46: Diversos | D46: Casinha plástica | E46: Telhado com chaminé | F46: Nº 4 | G46: Unidade | I46: =Instruções!$B$4 -> 0.4 | J46: =IF(H46="","",H46*(1+I46)) | N46: Foto 3 | O46: Volumoso, avaliar retirada e frete
A47: 45 | B47: Casa e conforto | C47: Diversos | D47: Caixa de transporte | E47: CONFIRMAR | F47: CONFIRMAR (nº) | G47: Unidade | I47: =Instruções!$B$4 -> 0.4 | J47: =IF(H47="","",H47*(1+I47)) | N47: Foto 5
A48: 46 | B48: Casa e conforto | C48: Diversos | D48: Cama / colchonete pet | E48: Diversas estampas | F48: CONFIRMAR | G48: Unidade | I48: =Instruções!$B$4 -> 0.4 | J48: =IF(H48="","",H48*(1+I48)) | N48: Foto 5 | O48: Prateleira ao fundo, levantar grade
A49: 47 | B49: Comedouro | C49: Diversos | D49: Comedouro e bebedouro plástico | E49: Diversas cores | F49: CONFIRMAR | G49: Unidade | I49: =Instruções!$B$4 -> 0.4 | J49: =IF(H49="","",H49*(1+I49)) | N49: Fotos 5 e 8
A50: 48 | B50: Comedouro | C50: Diversos | D50: Comedouro automático / dispenser | E50: Diversas cores | F50: CONFIRMAR | G50: Unidade | I50: =Instruções!$B$4 -> 0.4 | J50: =IF(H50="","",H50*(1+I50)) | N50: Foto 5
A51: 49 | B51: Higiene e banho | C51: CONFIRMAR | D51: Shampoo 2 em 1 (limpa e condiciona) | E51: Cães e gatos filhotes | F51: CONFIRMAR (frasco 700 ml aprox.) | G51: Unidade | I51: =Instruções!$B$4 -> 0.4 | J51: =IF(H51="","",H51*(1+I51)) | K51: 18 | N51: IMG_4298 | O51: CONFIRMAR marca e volume, etiqueta parcialmente legível
A52: 50 | B52: Higiene e banho | C52: CONFIRMAR | D52: Shampoo Vegetal com condicionador | E52: Melancia | F52: CONFIRMAR | G52: Unidade | I52: =Instruções!$B$4 -> 0.4 | J52: =IF(H52="","",H52*(1+I52)) | K52: 15 | N52: IMG_4298 | O52: CONFIRMAR marca e volume
A53: 51 | B53: Higiene e banho | C53: CONFIRMAR | D53: Shampoo Antiparasitário | E53: Antipulgas e carrapatos | F53: CONFIRMAR | G53: Unidade | I53: =Instruções!$B$4 -> 0.4 | J53: =IF(H53="","",H53*(1+I53)) | K53: 23 | N53: IMG_4298 | O53: Etiquetas de 23,00 e 24,00 na mesma fileira, CONFIRMAR variação
A54: 52 | B54: Higiene e banho | C54: CONFIRMAR | D54: Shampoo Clorexidina | E54: Antiqueda, antisséptico e antisseborreico | F54: CONFIRMAR (500 ml aprox.) | G54: Unidade | I54: =Instruções!$B$4 -> 0.4 | J54: =IF(H54="","",H54*(1+I54)) | K54: 25 | N54: IMG_4298 | O54: CONFIRMAR marca e volume
A55: 53 | B55: Higiene e banho | C55: CONFIRMAR | D55: Shampoo (frasco vermelho) | E55: CONFIRMAR | F55: CONFIRMAR | G55: Unidade | I55: =Instruções!$B$4 -> 0.4 | J55: =IF(H55="","",H55*(1+I55)) | N55: IMG_4298 | O55: Marca aparece cortada na foto, CONFIRMAR
A56: 54 | B56: Higiene e banho | C56: Diversos | D56: Toalha de secagem pet | E56: Diversas cores | F56: CONFIRMAR | G56: Unidade | I56: =Instruções!$B$4 -> 0.4 | J56: =IF(H56="","",H56*(1+I56)) | N56: IMG_4298 | O56: Aparece na prateleira lateral, CONFIRMAR marca e tamanho
A57: 55 | B57: Casa e conforto | C57: Diversos | D57: Manta / cobertor soft pet | E57: Azul e verde-limão | F57: CONFIRMAR | G57: Unidade | I57: =Instruções!$B$4 -> 0.4 | J57: =IF(H57="","",H57*(1+I57)) | N57: IMG_4297 | O57: CONFIRMAR medidas e grade de cores
A58: 56 | B58: Casa e conforto | C58: Diversos | D58: Colchonete / cama pet estampada | E58: Ossinhos, patinhas, ursinhos | F58: P / M / G | G58: Unidade | I58: =Instruções!$B$4 -> 0.4 | J58: =IF(H58="","",H58*(1+I58)) | K58: 100 | N58: IMG_4296 | O58: Etiqueta de 100,00 visível, CONFIRMAR a qual tamanho pertence
A59: 57 | B59: Acessório | C59: Napi | D59: Guia Retrátil | E59: Cães de raças pequenas até 15 kg | F59: Único | G59: Unidade | I59: =Instruções!$B$4 -> 0.4 | J59: =IF(H59="","",H59*(1+I59)) | K59: 28 | N59: IMG_4295
A60: 58 | B60: Brinquedo | C60: Diversos | D60: Mordedor de borracha | E60: Formatos variados | F60: Único | G60: Unidade | I60: =Instruções!$B$4 -> 0.4 | J60: =IF(H60="","",H60*(1+I60)) | K60: 7 | N60: IMG_4294 | O60: Vendido avulso no pote do balcão
A61: 59 | B61: Brinquedo | C61: Diversos | D61: Mordedor osso de borracha | E61: Roxo / vinho | F61: Único | G61: Unidade | I61: =Instruções!$B$4 -> 0.4 | J61: =IF(H61="","",H61*(1+I61)) | N61: IMG_4294 | O61: CONFIRMAR preço
A62: 60 | B62: Petisco gato | C62: Finotrato | D62: Cat Stix Snack Líquido Super Premium | E62: Salmão | F62: 15 g por sachê (caixa 540 g com 36) | G62: Sachê ou caixa | I62: =Instruções!$B$4 -> 0.4 | J62: =IF(H62="","",H62*(1+I62)) | K62: 25.2 | N62: IMG_4294 e IMG_4293 | O62: Há display de 6 unidades também, CONFIRMAR se 25,20 é a caixa ou o pack de 6
A63: 61 | B63: Alimento úmido gato | C63: Purina | D63: Friskies Sachê | E63: Carne ao molho | F63: 85 g | G63: Sachê | I63: =Instruções!$B$4 -> 0.4 | J63: =IF(H63="","",H63*(1+I63)) | K63: 3.7 | N63: IMG_4293
A64: 62 | B64: Alimento úmido gato | C64: Purina | D64: Friskies Sachê | E64: Salmão ao molho | F64: 85 g | G64: Sachê | I64: =Instruções!$B$4 -> 0.4 | J64: =IF(H64="","",H64*(1+I64)) | K64: 3.7 | N64: IMG_4293
A65: 63 | B65: Alimento úmido gato | C65: Purina | D65: Friskies Sachê | E65: Atum ao molho | F65: 85 g | G65: Sachê | I65: =Instruções!$B$4 -> 0.4 | J65: =IF(H65="","",H65*(1+I65)) | K65: 3.7 | N65: IMG_4293
A66: 64 | B66: Alimento úmido gato | C66: Purina | D66: Friskies Sachê | E66: Peixe branco ao molho | F66: 85 g | G66: Sachê | I66: =Instruções!$B$4 -> 0.4 | J66: =IF(H66="","",H66*(1+I66)) | K66: 3.7 | N66: IMG_4293
A67: 65 | B67: Alimento úmido gato | C67: Purina | D67: Friskies Sachê Filhotes | E67: Carne ao molho | F67: 85 g | G67: Sachê | I67: =Instruções!$B$4 -> 0.4 | J67: =IF(H67="","",H67*(1+I67)) | K67: 3.7 | N67: IMG_4293
A68: 66 | B68: Alimento úmido gato | C68: Special Cat | D68: Special Cat Ultralife Sachê | E68: Frango com batata-doce - gatos adultos | F68: CONFIRMAR (85 g) | G68: Sachê | I68: =Instruções!$B$4 -> 0.4 | J68: =IF(H68="","",H68*(1+I68)) | K68: 3.7 | N68: IMG_4293
A69: 67 | B69: Alimento úmido gato | C69: Gran Plus | D69: Gran Plus Gourmet Sachê | E69: Salmão - gato adulto | F69: CONFIRMAR (85 g) | G69: Sachê | I69: =Instruções!$B$4 -> 0.4 | J69: =IF(H69="","",H69*(1+I69)) | K69: 3.7 | N69: IMG_4291
A70: 68 | B70: Alimento úmido gato | C70: Gran Plus | D70: Gran Plus Gourmet Sachê | E70: Carne - gato adulto | F70: CONFIRMAR (85 g) | G70: Sachê | I70: =Instruções!$B$4 -> 0.4 | J70: =IF(H70="","",H70*(1+I70)) | K70: 3.7 | N70: IMG_4291
A71: 69 | B71: Alimento úmido gato | C71: Gran Plus | D71: Gran Plus Gourmet Sachê | E71: Atum - gato adulto | F71: CONFIRMAR (85 g) | G71: Sachê | I71: =Instruções!$B$4 -> 0.4 | J71: =IF(H71="","",H71*(1+I71)) | K71: 3.7 | N71: IMG_4291
A72: 70 | B72: Alimento úmido gato | C72: Gran Plus | D72: Gran Plus Gourmet Sachê | E72: Frango - gato adulto castrado | F72: CONFIRMAR (85 g) | G72: Sachê | I72: =Instruções!$B$4 -> 0.4 | J72: =IF(H72="","",H72*(1+I72)) | K72: 3.7 | N72: IMG_4291
A73: 71 | B73: Alimento úmido gato | C73: Gran Plus | D73: Gran Plus Gourmet Sachê | E73: Ovelha - gato adulto castrado | F73: CONFIRMAR (85 g) | G73: Sachê | I73: =Instruções!$B$4 -> 0.4 | J73: =IF(H73="","",H73*(1+I73)) | K73: 3.7 | N73: IMG_4291
A74: 72 | B74: Alimento úmido gato | C74: Gran Plus | D74: Gran Plus Gourmet Sachê | E74: Salmão e frango - gato adulto castrado | F74: CONFIRMAR (85 g) | G74: Sachê | I74: =Instruções!$B$4 -> 0.4 | J74: =IF(H74="","",H74*(1+I74)) | K74: 3.7 | N74: IMG_4291
... A79: 77 | B79: Alimento úmido cão | C79: Pedigree | D79: Pedigree Lata Adulto | E79: Carne patê | F79: 280 g | G79: Lata | I79: =Instruções!$B$4 -> 0.4 | J79: =IF(H79="","",H79*(1+I79)) | K79: 15 | N79: IMG_4292
A80: 78 | B80: Petisco cão | C80: Doogs | D80: Doogs Nuggets Dental Fresh | E80: Menta - hálito refrescante | F80: CONFIRMAR | G80: Pacote | I80: =Instruções!$B$4 -> 0.4 | J80: =IF(H80="","",H80*(1+I80)) | K80: 6.4 | N80: IMG_4290 e IMG_4289 | O80: Com Yucca schidigera e probióticos
A81: 79 | B81: Petisco cão | C81: Unna | D81: Bifinho Unna | E81: Carne | F81: CONFIRMAR | G81: Pacote | I81: =Instruções!$B$4 -> 0.4 | J81: =IF(H81="","",H81*(1+I81)) | K81: 4.5 | N81: IMG_4289 | O81: Etiqueta na caixa display, CONFIRMAR se é preço unitário
A82: 80 | B82: Petisco cão | C82: Batuta | D82: Batuta Bifinhos Super Premium | E82: Carne | F82: 200 g | G82: Pacote | I82: =Instruções!$B$4 -> 0.4 | J82: =IF(H82="","",H82*(1+I82)) | K82: 9.5 | N82: IMG_4289
A83: 81 | B83: Petisco cão | C83: CONFIRMAR | D83: Bifinho (embalagem amarela) | E83: CONFIRMAR | F83: CONFIRMAR | G83: Pacote | I83: =Instruções!$B$4 -> 0.4 | J83: =IF(H83="","",H83*(1+I83)) | N83: IMG_4289 | O83: Marca não legível na foto, CONFIRMAR
A84: 82 | B84: Alimento úmido cão | C84: Purina | D84: Dog Chow Extra Life Sachê | E84: Frango - adultos minis e pequenos | F84: CONFIRMAR (100 g) | G84: Sachê | I84: =Instruções!$B$4 -> 0.4 | J84: =IF(H84="","",H84*(1+I84)) | K84: 4 | N84: IMG_4288
A85: 83 | B85: Alimento úmido cão | C85: Purina | D85: Dog Chow Extra Life Sachê | E85: Frango - adultos todos os tamanhos | F85: CONFIRMAR (100 g) | G85: Sachê | I85: =Instruções!$B$4 -> 0.4 | J85: =IF(H85="","",H85*(1+I85)) | K85: 4 | N85: IMG_4288
A86: 84 | B86: Alimento úmido cão | C86: Purina | D86: Dog Chow Nutrição Reforçada Sachê | E86: Adulto todos os tamanhos | F86: CONFIRMAR (100 g) | G86: Sachê | I86: =Instruções!$B$4 -> 0.4 | J86: =IF(H86="","",H86*(1+I86)) | K86: 4 | N86: IMG_4288
A87: 85 | B87: Alimento úmido cão | C87: Kelco | D87: Sachê Kelco (Kelldog) | E87: Frango com ervilha e cenoura | F87: CONFIRMAR (100 g) | G87: Sachê | I87: =Instruções!$B$4 -> 0.4 | J87: =IF(H87="","",H87*(1+I87)) | K87: 3.2 | N87: IMG_4288 | O87: CONFIRMAR nome exato da linha
A88: 86 | B88: Alimento úmido cão | C88: Kelco | D88: Sachê Kelco (Kelldog) | E88: Carne com ervilha e cenoura | F88: CONFIRMAR (100 g) | G88: Sachê | I88: =Instruções!$B$4 -> 0.4 | J88: =IF(H88="","",H88*(1+I88)) | K88: 3.2 | N88: IMG_4288 | O88: CONFIRMAR nome exato da linha
A89: 87 | B89: Alimento úmido cão | C89: Gran Plus | D89: Gran Plus Gourmet Sachê | E89: Carne - cão adulto | F89: CONFIRMAR (100 g) | G89: Sachê | I89: =Instruções!$B$4 -> 0.4 | J89: =IF(H89="","",H89*(1+I89)) | K89: 4 | N89: IMG_4288
A90: 88 | B90: Alimento úmido cão | C90: Gran Plus | D90: Gran Plus Gourmet Sachê | E90: Frango - cão adulto | F90: CONFIRMAR (100 g) | G90: Sachê | I90: =Instruções!$B$4 -> 0.4 | J90: =IF(H90="","",H90*(1+I90)) | K90: 4 | N90: IMG_4288
A91: 89 | B91: Alimento úmido gato | C91: Origens | D91: Origens Sachê Gato Castrado | E91: Frango e carne | F91: CONFIRMAR (85 g) | G91: Sachê | I91: =Instruções!$B$4 -> 0.4 | J91: =IF(H91="","",H91*(1+I91)) | N91: IMG_4287 e IMG_4286 | O91: Caixa fechada na prateleira, CONFIRMAR preço e sabores
A92: 90 | B92: Petisco cão | C92: Paladar Canino | D92: Palito mastigável natural 8 mm | E92: Natural | F92: 1 kg (105 unidades) | G92: Pacote | I92: =Instruções!$B$4 -> 0.4 | J92: =IF(H92="","",H92*(1+I92)) | K92: 22 | N92: IMG_4287 | O92: Também pode ser vendido por unidade, CONFIRMAR
A93: 91 | B93: Petisco cão | C93: Gran Plus | D93: Gran Plus Biscoitos | E93: Leite - cães filhotes de todos os portes | F93: CONFIRMAR (200 g) | G93: Pacote | I93: =Instruções!$B$4 -> 0.4 | J93: =IF(H93="","",H93*(1+I93)) | K93: 14.4 | N93: IMG_4287 e IMG_4286
A94: 92 | B94: Petisco cão | C94: Special Dog | D94: Special Dog Ultralife Biscoitos Assados Filhotes | E94: Frutas vermelhas | F94: 250 g | G94: Pacote | I94: =Instruções!$B$4 -> 0.4 | J94: =IF(H94="","",H94*(1+I94)) | K94: 16.3 | N94: IMG_4286 | O94: Peso confirmado nesta foto: 250 g
A95: 93 | B95: Casa e conforto | C95: CONFIRMAR | D95: Cama redonda / toca pet | E95: Preta com rosa, preta com vermelho | F95: CONFIRMAR | G95: Unidade | I95: =Instruções!$B$4 -> 0.4 | J95: =IF(H95="","",H95*(1+I95)) | N95: IMG_4284 | O95: CONFIRMAR marca, tamanhos e preços
A96: 94 | B96: Casa e conforto | C96: CONFIRMAR | D96: Almofada / colchonete estampado | E96: Gatinhos, patinhas, ossinhos | F96: P / M / G | G96: Unidade | I96: =Instruções!$B$4 -> 0.4 | J96: =IF(H96="","",H96*(1+I96)) | N96: IMG_4283 e IMG_4285 | O96: Etiqueta de marca aparece cortada, CONFIRMAR fabricante
A97: 95 | B97: Casa e conforto | C97: Diversos | D97: Caixa de transporte plástica | E97: Porta rosa, azul e roxa | F97: CONFIRMAR (nº 1 / 2 / 3) | G97: Unidade | I97: =Instruções!$B$4 -> 0.4 | J97: =IF(H97="","",H97*(1+I97)) | K97: 55.8 | N97: IMG_4282 | O97: CONFIRMAR a qual tamanho a etiqueta pertence
A98: 96 | B98: Casa e conforto | C98: Diversos | D98: Caixa de transporte (modelo branco) | E98: Branca | F98: CONFIRMAR | G98: Unidade | I98: =Instruções!$B$4 -> 0.4 | J98: =IF(H98="","",H98*(1+I98)) | K98: 35 | N98: IMG_4282 | O98: CONFIRMAR se é caixa de transporte ou banheiro
A99: 97 | B99: Higiene | C99: Diversos | D99: Bandeja sanitária com grade | E99: Vermelha, rosa e vinho | F99: CONFIRMAR | G99: Unidade | I99: =Instruções!$B$4 -> 0.4 | J99: =IF(H99="","",H99*(1+I99)) | K99: 20 | N99: IMG_4280
A100: 98 | B100: Higiene | C100: Cleaning Cats | D100: Granulado higiênico de madeira | E100: Gatos | F100: 10 kg | G100: Saco | I100: =Instruções!$B$4 -> 0.4 | J100: =IF(H100="","",H100*(1+I100)) | N100: IMG_4280 e IMG_4279 | O100: CONFIRMAR preço
A101: 99 | B101: Higiene | C101: Diversos | D101: Borrifador / pulverizador manual | E101: Tampa vermelha e rosa | F101: CONFIRMAR (500 ml) | G101: Unidade | I101: =Instruções!$B$4 -> 0.4 | J101: =IF(H101="","",H101*(1+I101)) | K101: 10 | N101: IMG_4281
A102: 100 | B102: Acessório | C102: Diversos | D102: Colar elizabetano | E102: Gatos | F102: CONFIRMAR (tamanhos variados) | G102: Unidade | I102: =Instruções!$B$4 -> 0.4 | J102: =IF(H102="","",H102*(1+I102)) | N102: IMG_4281 | O102: Etiqueta pouco legível, CONFIRMAR preço
A103: 101 | B103: Acessório | C103: Diversos | D103: Avental / capa de tosa | E103: Preto | F103: Único | G103: Unidade | I103: =Instruções!$B$4 -> 0.4 | J103: =IF(H103="","",H103*(1+I103)) | K103: 40 | N103: IMG_4281 | O103: CONFIRMAR se é avental de tosa ou capa
A104: 102 | B104: Outros animais | C104: Diversos | D104: Alpiste a granel | E104: Pássaros | F104: Por kg | G104: Quilo | I104: =Instruções!$B$4 -> 0.4 | J104: =IF(H104="","",H104*(1+I104)) | K104: 19.5 | N104: IMG_4281 | O104: Venda a granel, CONFIRMAR fracionamento para o marketplace
...

Sheet Campos da plataforma
A1: Campos mínimos para cadastrar um produto no marketplace Saúde Pet
A3: Campo | B3: Obrigatório | C3: Observação
A4: SKU interno | B4: Sim | C4: Padrão sugerido: FOR01-CATEGORIA-0001 (FOR01 = Filhos de 4 Patas)
A5: Nome do produto | B5: Sim | C5: Marca + linha + sabor + peso. Ex: Golden Formula Adultos Frango e Arroz 15 kg
A6: Código de barras (EAN) | B6: Sim | C6: Evita duplicidade quando entrarem novos fornecedores
A7: Categoria e subcategoria | B7: Sim | C7: Cão / Gato / Pássaro > Ração, Petisco, Higiene, Acessório
A8: Marca | B8: Sim | C8: Vira filtro na busca
A9: Peso ou tamanho | B9: Sim | C9: Também usado no cálculo de frete
A10: Peso bruto para frete | B10: Sim | C10: Saco de 15 kg muda a logística de retirada e entrega
A11: Custo do fornecedor | B11: Sim | C11: Não aparece para o cliente
A12: Margem aplicada | B12: Sim | C12: Padrão 40%, ajustável por item
A13: Preço de venda | B13: Sim | C13: Gerado pelo custo x margem
A14: Estoque ou disponibilidade | B14: Sim | C14: Se for sob encomenda, informar prazo na descrição
... A18: Prazo de reposição | B18: Não | C18: Útil quando o item estiver zerado
